MANIFEST.in
README.md
setup.py
cssbench/__init__.py
cssbench/compiler/benchmark/clean.sh
cssbench/compiler/benchmark/init.sh
cssbench/compiler/benchmark/run.py
cssbench/compiler/benchmark/run.sh
cssbench/compiler/benchmark/dataset/adpcm-0001/data.adpcm
cssbench/compiler/benchmark/dataset/au-0001/data.au
cssbench/compiler/benchmark/dataset/audio-mp3-0001/data.mp3
cssbench/compiler/benchmark/dataset/bzip2-0001/data
cssbench/compiler/benchmark/dataset/bzip2-0001/data.bz2
cssbench/compiler/benchmark/dataset/cdataset-dijkstra-0001/data.txt
cssbench/compiler/benchmark/dataset/cdataset-patricia-0001/data.txt
cssbench/compiler/benchmark/dataset/cdataset-qsort-0001/data.txt
cssbench/compiler/benchmark/dataset/enc-0001/data.enc
cssbench/compiler/benchmark/dataset/image-jpeg-0001/data.jpg
cssbench/compiler/benchmark/dataset/image-jpeg-dnn-computer-mouse/README
cssbench/compiler/benchmark/dataset/image-jpeg-dnn-computer-mouse/computer_mouse.jpg
cssbench/compiler/benchmark/dataset/image-pgm-from-pamela-100/README.txt
cssbench/compiler/benchmark/dataset/image-pgm-from-pamela-100/data.pgm
cssbench/compiler/benchmark/dataset/image-pgm-from-pamela-100/scene_00_0100.depth
cssbench/compiler/benchmark/dataset/image-pgm-from-pamela-100/scene_00_0100.png
cssbench/compiler/benchmark/dataset/image-pgm-from-pamela-100/scene_00_0100.txt
cssbench/compiler/benchmark/dataset/image-ppm-0001/data.ppm
cssbench/compiler/benchmark/dataset/image-tiff-0001/data.tiff
cssbench/compiler/benchmark/dataset/image-tiff-0001-bw/data.tiff
cssbench/compiler/benchmark/dataset/pcm-0001/data.pcm
cssbench/compiler/benchmark/dataset/pgp-0001/data.pgp
cssbench/compiler/benchmark/dataset/txt-0001/data.s.txt
cssbench/compiler/benchmark/dataset/txt-0001/data.txt
cssbench/compiler/benchmark/packages/papi701.tar.gz
cssbench/compiler/benchmark/packages/polybench.tar.gz
cssbench/compiler/benchmark/programs/cbench-automotive-bitcount/LICENSE
cssbench/compiler/benchmark/programs/cbench-automotive-bitcount/Makefile
csstuning.egg-info/PKG-INFO
csstuning.egg-info/SOURCES.txt
csstuning.egg-info/dependency_links.txt
csstuning.egg-info/entry_points.txt
csstuning.egg-info/not-zip-safe
csstuning.egg-info/requires.txt
csstuning.egg-info/top_level.txt
