Metadata-Version: 2.1
Name: csstuning
Version: 0.0.1
Summary: Configurable Software System Tuning Benchmark
Home-page: https://github.com/neeetman/csstuning
Author: An Shao
Author-email: anshaohac@gmail.com
License: UNKNOWN
Platform: UNKNOWN
Classifier: Programming Language :: Python :: 3.8
Classifier: License :: OSI Approved :: MIT License
Classifier: Operating System :: POSIX :: Linux
Requires-Python: >=3.8
